[
  {
    "rank": 1,
    "symbol": "QPOWER",
    "name": "Quality Power El",
    "prerank_score": 89.86,
    "qpv": 169.18,
    "qsv": 291.22,
    "roce": 26.6,
    "ret3m": 91.84,
    "cmp": 1265.35,
    "pe": 91.54,
    "mcap": 9795.94,
    "divyld": 0.08,
    "npqtr": 62.76,
    "salesqtr": 283.99,
    "flags": [],
    "in_working_universe": true
  },
  {
    "rank": 2,
    "symbol": "LLOYDSME",
    "name": "Lloyds Metals",
    "prerank_score": 88.67,
    "qpv": 169.05,
    "qsv": 201.94,
    "roce": 38.28,
    "ret3m": 44.45,
    "cmp": 1649.9,
    "pe": 37.72,
    "mcap": 92922.36,
    "divyld": 0.06,
    "npqtr": 1089.56,
    "salesqtr": 5058.08,
    "flags": [],
    "in_working_universe": true
  },
  {
    "rank": 3,
    "symbol": "ATLANTAELE",
    "name": "Atlanta Electric",
    "prerank_score": 86.24,
    "qpv": 125.33,
    "qsv": 79.71,
    "roce": 50.2,
    "ret3m": 83.21,
    "cmp": 1377.0,
    "pe": 67.78,
    "mcap": 10585.99,
    "divyld": 0.0,
    "npqtr": 49.42,
    "salesqtr": 471.82,
    "flags": [],
    "in_working_universe": true
  },
  {
    "rank": 4,
    "symbol": "WAAREEENER",
    "name": "Waaree Energies",
    "prerank_score": 86.01,
    "qpv": 158.06,
    "qsv": 118.81,
    "roce": 34.94,
    "ret3m": 43.56,
    "cmp": 3472.8,
    "pe": 28.71,
    "mcap": 99949.99,
    "divyld": 0.06,
    "npqtr": 1106.79,
    "salesqtr": 7565.05,
    "flags": [],
    "in_working_universe": true
  },
  {
    "rank": 5,
    "symbol": "INSOLATION",
    "name": "Insolation Ener",
    "prerank_score": 84.2,
    "qpv": 173.57,
    "qsv": 77.05,
    "roce": 34.73,
    "ret3m": 41.13,
    "cmp": 143.6,
    "pe": 17.85,
    "mcap": 3161.99,
    "divyld": 0.07,
    "npqtr": 50.72,
    "salesqtr": 575.34,
    "flags": [],
    "in_working_universe": true
  },
  {
    "rank": 6,
    "symbol": "GVT&D",
    "name": "GE Vernova T&D",
    "prerank_score": 83.56,
    "qpv": 138.53,
    "qsv": 58.4,
    "roce": 54.74,
    "ret3m": 66.24,
    "cmp": 4252.1,
    "pe": 97.42,
    "mcap": 108863.44,
    "divyld": 0.12,
    "npqtr": 290.8,
    "salesqtr": 1700.64,
    "flags": [],
    "in_working_universe": true
  },
  {
    "rank": 7,
    "symbol": "SAATVIKGL",
    "name": "Saatvik Green",
    "prerank_score": 82.4,
    "qpv": 144.05,
    "qsv": 142.58,
    "roce": 52.33,
    "ret3m": 31.36,
    "cmp": 461.85,
    "pe": 14.97,
    "mcap": 5867.19,
    "divyld": 0.0,
    "npqtr": 98.72,
    "salesqtr": 1257.02,
    "flags": [],
    "in_working_universe": true
  },
  {
    "rank": 8,
    "symbol": "BSE",
    "name": "BSE",
    "prerank_score": 81.74,
    "qpv": 175.79,
    "qsv": 61.97,
    "roce": 46.57,
    "ret3m": 33.74,
    "cmp": 3515.8,
    "pe": 65.64,
    "mcap": 143198.21,
    "divyld": 0.17,
    "npqtr": 596.59,
    "salesqtr": 1244.1,
    "flags": [],
    "in_working_universe": true
  },
  {
    "rank": 9,
    "symbol": "ORIANA",
    "name": "Oriana Power Ltd",
    "prerank_score": 81.3,
    "qpv": 149.88,
    "qsv": 117.27,
    "roce": 42.31,
    "ret3m": 30.53,
    "cmp": 2120.35,
    "pe": 18.62,
    "mcap": 4308.37,
    "divyld": 0.0,
    "npqtr": 121.63,
    "salesqtr": 781.18,
    "flags": [],
    "in_working_universe": true
  },
  {
    "rank": 10,
    "symbol": "EMMVEE",
    "name": "Emmvee Photovol.",
    "prerank_score": 80.79,
    "qpv": 165.77,
    "qsv": 118.11,
    "roce": 28.01,
    "ret3m": 33.77,
    "cmp": 261.31,
    "pe": 33.94,
    "mcap": 18104.84,
    "divyld": 0.0,
    "npqtr": 263.64,
    "salesqtr": 1152.25,
    "flags": [],
    "in_working_universe": true
  },
  {
    "rank": 11,
    "symbol": "CUPID",
    "name": "Cupid",
    "prerank_score": 79.39,
    "qpv": 196.66,
    "qsv": 105.67,
    "roce": 17.1,
    "ret3m": 45.94,
    "cmp": 109.92,
    "pe": 176.68,
    "mcap": 14763.7,
    "divyld": 0.0,
    "npqtr": 32.87,
    "salesqtr": 104.4,
    "flags": [],
    "in_working_universe": true
  },
  {
    "rank": 12,
    "symbol": "ENGINERSIN",
    "name": "Engineers India",
    "prerank_score": 77.27,
    "qpv": 219.3,
    "qsv": 58.29,
    "roce": 25.01,
    "ret3m": 36.23,
    "cmp": 243.24,
    "pe": 17.63,
    "mcap": 13677.34,
    "divyld": 1.64,
    "npqtr": 347.17,
    "salesqtr": 1210.24,
    "flags": [],
    "in_working_universe": true
  },
  {
    "rank": 13,
    "symbol": "IDEAFORGE",
    "name": "Billionbrains",
    "prerank_score": 76.59,
    "qpv": 122.06,
    "qsv": 87.93,
    "roce": 37.38,
    "ret3m": 32.7,
    "cmp": 214.01,
    "pe": 64.34,
    "mcap": 134028.87,
    "divyld": 0.0,
    "npqtr": 686.35,
    "salesqtr": 1505.37,
    "flags": [],
    "in_working_universe": true
  },
  {
    "rank": 14,
    "symbol": "KRISHANA",
    "name": "Krishana Phosch.",
    "prerank_score": 75.09,
    "qpv": 152.83,
    "qsv": 59.76,
    "roce": 27.24,
    "ret3m": 32.56,
    "cmp": 623.65,
    "pe": 20.96,
    "mcap": 3776.37,
    "divyld": 0.08,
    "npqtr": 83.08,
    "salesqtr": 755.49,
    "flags": [],
    "in_working_universe": true
  },
  {
    "rank": 15,
    "symbol": "MANORAMA",
    "name": "Manorama Indust.",
    "prerank_score": 72.22,
    "qpv": 131.09,
    "qsv": 73.3,
    "roce": 23.03,
    "ret3m": 32.74,
    "cmp": 1447.7,
    "pe": 39.95,
    "mcap": 8628.42,
    "divyld": 0.04,
    "npqtr": 68.24,
    "salesqtr": 362.54,
    "flags": [],
    "in_working_universe": true
  },
  {
    "rank": 16,
    "symbol": "ACUTAAS",
    "name": "Acutaas Chemical",
    "prerank_score": 70.46,
    "qpv": 140.18,
    "qsv": 42.98,
    "roce": 19.92,
    "ret3m": 48.17,
    "cmp": 2374.4,
    "pe": 67.73,
    "mcap": 19435.85,
    "divyld": 0.06,
    "npqtr": 106.22,
    "salesqtr": 393.18,
    "flags": [],
    "in_working_universe": true
  },
  {
    "rank": 17,
    "symbol": "BAJAJCON",
    "name": "Bajaj Consumer",
    "prerank_score": 70.28,
    "qpv": 105.29,
    "qsv": 30.41,
    "roce": 30.6,
    "ret3m": 85.45,
    "cmp": 458.9,
    "pe": 31.52,
    "mcap": 5994.08,
    "divyld": 0.0,
    "npqtr": 63.6,
    "salesqtr": 326.66,
    "flags": [],
    "in_working_universe": true
  },
  {
    "rank": 18,
    "symbol": "PRECWIRE",
    "name": "Prec. Wires (I)",
    "prerank_score": 69.78,
    "qpv": 98.94,
    "qsv": 37.19,
    "roce": 26.78,
    "ret3m": 76.65,
    "cmp": 386.95,
    "pe": 54.41,
    "mcap": 7072.78,
    "divyld": 0.3,
    "npqtr": 37.7,
    "salesqtr": 1347.61,
    "flags": [],
    "in_working_universe": true
  },
  {
    "rank": 19,
    "symbol": "SHARDACROP",
    "name": "Sharda Cropchem",
    "prerank_score": 69.58,
    "qpv": 365.87,
    "qsv": 38.68,
    "roce": 16.5,
    "ret3m": 37.98,
    "cmp": 1107.9,
    "pe": 17.69,
    "mcap": 10006.88,
    "divyld": 0.81,
    "npqtr": 145.11,
    "salesqtr": 1288.76,
    "flags": [],
    "in_working_universe": true
  },
  {
    "rank": 20,
    "symbol": "RUBICON",
    "name": "Rubicon Research",
    "prerank_score": 69.42,
    "qpv": 91.23,
    "qsv": 51.73,
    "roce": 26.05,
    "ret3m": 39.73,
    "cmp": 921.35,
    "pe": 89.88,
    "mcap": 15139.29,
    "divyld": 0.0,
    "npqtr": 72.8,
    "salesqtr": 475.53,
    "flags": [],
    "in_working_universe": true
  },
  {
    "rank": 21,
    "symbol": "CPPLUS",
    "name": "Aditya Infotech",
    "prerank_score": 68.85,
    "qpv": 138.82,
    "qsv": 37.32,
    "roce": 19.49,
    "ret3m": 64.05,
    "cmp": 2258.0,
    "pe": 104.75,
    "mcap": 26584.78,
    "divyld": 0.0,
    "npqtr": 95.98,
    "salesqtr": 1139.11,
    "flags": [],
    "in_working_universe": false
  },
  {
    "rank": 22,
    "symbol": "EBGNG",
    "name": "GNG Electronics",
    "prerank_score": 66.35,
    "qpv": 102.78,
    "qsv": 40.26,
    "roce": 19.84,
    "ret3m": 62.52,
    "cmp": 415.65,
    "pe": 45.3,
    "mcap": 4739.46,
    "divyld": 0.0,
    "npqtr": 38.69,
    "salesqtr": 487.22,
    "flags": [],
    "in_working_universe": false
  },
  {
    "rank": 23,
    "symbol": "KRN",
    "name": "KRN Heat Exchan",
    "prerank_score": 65.88,
    "qpv": 65.04,
    "qsv": 37.46,
    "roce": 20.75,
    "ret3m": 95.39,
    "cmp": 1212.8,
    "pe": 111.02,
    "mcap": 7545.92,
    "divyld": 0.0,
    "npqtr": 22.66,
    "salesqtr": 153.23,
    "flags": [],
    "in_working_universe": false
  },
  {
    "rank": 24,
    "symbol": "SEAMECLTD",
    "name": "SEAMEC Ltd",
    "prerank_score": 65.84,
    "qpv": 3100.6,
    "qsv": 112.3,
    "roce": 8.6,
    "ret3m": 39.14,
    "cmp": 1519.1,
    "pe": 20.26,
    "mcap": 3867.15,
    "divyld": 0.0,
    "npqtr": 99.76,
    "salesqtr": 317.05,
    "flags": [
      "low_roce"
    ],
    "in_working_universe": false
  },
  {
    "rank": 25,
    "symbol": "RRWL",
    "name": "Ram Ratna Wires",
    "prerank_score": 64.91,
    "qpv": 106.33,
    "qsv": 43.8,
    "roce": 20.17,
    "ret3m": 38.35,
    "cmp": 389.65,
    "pe": 41.18,
    "mcap": 3651.07,
    "divyld": 0.32,
    "npqtr": 31.64,
    "salesqtr": 1277.94,
    "flags": [],
    "in_working_universe": false
  },
  {
    "rank": 26,
    "symbol": "POWERINDIA",
    "name": "Hitachi Energy",
    "prerank_score": 64.31,
    "qpv": 119.97,
    "qsv": 28.51,
    "roce": 19.44,
    "ret3m": 79.1,
    "cmp": 29890.0,
    "pe": 151.01,
    "mcap": 133193.78,
    "divyld": 0.02,
    "npqtr": 261.42,
    "salesqtr": 2082.21,
    "flags": [],
    "in_working_universe": false
  },
  {
    "rank": 27,
    "symbol": "HIRECT",
    "name": "Hind Rectifiers",
    "prerank_score": 63.11,
    "qpv": 47.85,
    "qsv": 44.0,
    "roce": 21.6,
    "ret3m": 43.41,
    "cmp": 894.6,
    "pe": 58.65,
    "mcap": 3079.93,
    "divyld": 0.11,
    "npqtr": 13.73,
    "salesqtr": 243.27,
    "flags": [],
    "in_working_universe": false
  },
  {
    "rank": 28,
    "symbol": "ENRIN",
    "name": "Siemens Ener.Ind",
    "prerank_score": 62.43,
    "qpv": 51.67,
    "qsv": 25.97,
    "roce": 67.75,
    "ret3m": 42.53,
    "cmp": 3208.2,
    "pe": 93.66,
    "mcap": 114250.58,
    "divyld": 0.12,
    "npqtr": 312.9,
    "salesqtr": 1910.9,
    "flags": [],
    "in_working_universe": false
  },
  {
    "rank": 29,
    "symbol": "DATAPATTNS",
    "name": "Data Pattern",
    "prerank_score": 62.17,
    "qpv": 35.76,
    "qsv": 47.92,
    "roce": 21.0,
    "ret3m": 59.23,
    "cmp": 3526.4,
    "pe": 79.15,
    "mcap": 19740.76,
    "divyld": 0.22,
    "npqtr": 58.3,
    "salesqtr": 173.13,
    "flags": [],
    "in_working_universe": false
  },
  {
    "rank": 30,
    "symbol": "MTARTECH",
    "name": "MTAR Technologie",
    "prerank_score": 61.82,
    "qpv": 131.84,
    "qsv": 59.3,
    "roce": 10.51,
    "ret3m": 108.06,
    "cmp": 5071.1,
    "pe": 229.68,
    "mcap": 15590.45,
    "divyld": 0.0,
    "npqtr": 35.17,
    "salesqtr": 277.9,
    "flags": [
      "low_roce"
    ],
    "in_working_universe": false
  },
  {
    "rank": 31,
    "symbol": "SAMBHV",
    "name": "Sambhv Steel",
    "prerank_score": 58.77,
    "qpv": 112.79,
    "qsv": 59.64,
    "roce": 13.92,
    "ret3m": 42.8,
    "cmp": 119.92,
    "pe": 33.94,
    "mcap": 3528.41,
    "divyld": 0.0,
    "npqtr": 24.13,
    "salesqtr": 589.14,
    "flags": [
      "low_roce"
    ],
    "in_working_universe": false
  },
  {
    "rank": 32,
    "symbol": "VOLTAMP",
    "name": "Volt.Transform.",
    "prerank_score": 58.71,
    "qpv": 34.99,
    "qsv": 30.36,
    "roce": 29.11,
    "ret3m": 55.26,
    "cmp": 10524.5,
    "pe": 30.09,
    "mcap": 10660.85,
    "divyld": 0.95,
    "npqtr": 99.08,
    "salesqtr": 630.32,
    "flags": [],
    "in_working_universe": false
  },
  {
    "rank": 33,
    "symbol": "SGFIN",
    "name": "SG Finserve",
    "prerank_score": 56.43,
    "qpv": 77.68,
    "qsv": 94.88,
    "roce": 9.32,
    "ret3m": 49.52,
    "cmp": 541.4,
    "pe": 27.97,
    "mcap": 3571.15,
    "divyld": 0.0,
    "npqtr": 42.27,
    "salesqtr": 105.41,
    "flags": [
      "low_roce"
    ],
    "in_working_universe": false
  },
  {
    "rank": 34,
    "symbol": "TDPOWERSYS",
    "name": "TD Power Systems",
    "prerank_score": 55.4,
    "qpv": 25.35,
    "qsv": 26.36,
    "roce": 30.35,
    "ret3m": 60.2,
    "cmp": 1017.45,
    "pe": 72.4,
    "mcap": 15898.7,
    "divyld": 0.12,
    "npqtr": 56.32,
    "salesqtr": 442.68,
    "flags": [],
    "in_working_universe": false
  },
  {
    "rank": 35,
    "symbol": "SYRMA",
    "name": "Syrma SGS Tech.",
    "prerank_score": 55.28,
    "qpv": 108.8,
    "qsv": 45.36,
    "roce": 11.67,
    "ret3m": 54.02,
    "cmp": 985.95,
    "pe": 66.84,
    "mcap": 19018.04,
    "divyld": 0.15,
    "npqtr": 110.32,
    "salesqtr": 1264.18,
    "flags": [
      "low_roce"
    ],
    "in_working_universe": false
  },
  {
    "rank": 36,
    "symbol": "PFOCUS",
    "name": "Prime Focus",
    "prerank_score": 54.96,
    "qpv": 237.06,
    "qsv": 32.74,
    "roce": 7.95,
    "ret3m": 49.77,
    "cmp": 328.2,
    "pe": 96.82,
    "mcap": 25468.01,
    "divyld": 0.0,
    "npqtr": 69.2,
    "salesqtr": 1207.24,
    "flags": [
      "low_roce"
    ],
    "in_working_universe": false
  },
  {
    "rank": 37,
    "symbol": "TRIL",
    "name": "T R I L",
    "prerank_score": 54.76,
    "qpv": 34.89,
    "qsv": 31.71,
    "roce": 27.97,
    "ret3m": 36.94,
    "cmp": 333.3,
    "pe": 37.52,
    "mcap": 10007.64,
    "divyld": 0.06,
    "npqtr": 75.97,
    "salesqtr": 736.76,
    "flags": [],
    "in_working_universe": false
  },
  {
    "rank": 38,
    "symbol": "RASHI",
    "name": "Rashi Peripheral",
    "prerank_score": 53.15,
    "qpv": 131.0,
    "qsv": 42.6,
    "roce": 14.19,
    "ret3m": 34.68,
    "cmp": 474.35,
    "pe": 12.87,
    "mcap": 3125.62,
    "divyld": 0.42,
    "npqtr": 74.6,
    "salesqtr": 4030.41,
    "flags": [
      "low_roce"
    ],
    "in_working_universe": false
  },
  {
    "rank": 39,
    "symbol": "INOXINDIA",
    "name": "Inox India",
    "prerank_score": 52.98,
    "qpv": 26.34,
    "qsv": 28.45,
    "roce": 37.98,
    "ret3m": 34.12,
    "cmp": 1482.6,
    "pe": 53.21,
    "mcap": 13454.77,
    "divyld": 0.13,
    "npqtr": 60.7,
    "salesqtr": 428.56,
    "flags": [],
    "in_working_universe": false
  },
  {
    "rank": 40,
    "symbol": "CGPOWER",
    "name": "CG Power & Ind",
    "prerank_score": 52.2,
    "qpv": 18.42,
    "qsv": 26.22,
    "roce": 37.48,
    "ret3m": 39.97,
    "cmp": 805.25,
    "pe": 113.84,
    "mcap": 126670.55,
    "divyld": 0.16,
    "npqtr": 283.91,
    "salesqtr": 3175.35,
    "flags": [],
    "in_working_universe": false
  },
  {
    "rank": 41,
    "symbol": "DYNAMATECH",
    "name": "Dynamatic Tech.",
    "prerank_score": 51.76,
    "qpv": 316.15,
    "qsv": 34.7,
    "roce": 8.96,
    "ret3m": 34.17,
    "cmp": 10747.0,
    "pe": 155.69,
    "mcap": 7289.52,
    "divyld": 0.05,
    "npqtr": 5.77,
    "salesqtr": 424.87,
    "flags": [
      "low_roce"
    ],
    "in_working_universe": false
  },
  {
    "rank": 42,
    "symbol": "SCI",
    "name": "S C I",
    "prerank_score": 51.63,
    "qpv": 436.24,
    "qsv": 22.5,
    "roce": 9.81,
    "ret3m": 48.34,
    "cmp": 300.6,
    "pe": 12.34,
    "mcap": 13986.1,
    "divyld": 2.19,
    "npqtr": 404.97,
    "salesqtr": 1611.67,
    "flags": [
      "low_roce"
    ],
    "in_working_universe": false
  },
  {
    "rank": 43,
    "symbol": "SCHNEIDER",
    "name": "Schneider Elect.",
    "prerank_score": 51.33,
    "qpv": 16.65,
    "qsv": 20.06,
    "roce": 40.9,
    "ret3m": 82.8,
    "cmp": 1058.8,
    "pe": 97.04,
    "mcap": 25392.93,
    "divyld": 0.0,
    "npqtr": 97.03,
    "salesqtr": 1029.17,
    "flags": [],
    "in_working_universe": false
  },
  {
    "rank": 44,
    "symbol": "PREMIERENE",
    "name": "Premier Energies",
    "prerank_score": 51.21,
    "qpv": 53.48,
    "qsv": 13.02,
    "roce": 41.12,
    "ret3m": 40.0,
    "cmp": 995.7,
    "pe": 33.92,
    "mcap": 45140.38,
    "divyld": 0.1,
    "npqtr": 391.62,
    "salesqtr": 1936.46,
    "flags": [],
    "in_working_universe": false
  },
  {
    "rank": 45,
    "symbol": "GEPIL",
    "name": "GE Power",
    "prerank_score": 50.64,
    "qpv": 431.62,
    "qsv": 21.69,
    "roce": 6.09,
    "ret3m": 75.97,
    "cmp": 492.0,
    "pe": 19.6,
    "mcap": 3291.39,
    "divyld": 0.0,
    "npqtr": 72.32,
    "salesqtr": 385.62,
    "flags": [
      "low_roce"
    ],
    "in_working_universe": false
  },
  {
    "rank": 46,
    "symbol": "AXISCADES",
    "name": "AXISCADES Tech.",
    "prerank_score": 48.97,
    "qpv": 110.65,
    "qsv": 25.01,
    "roce": 13.76,
    "ret3m": 71.26,
    "cmp": 1916.7,
    "pe": 74.03,
    "mcap": 8122.39,
    "divyld": 0.0,
    "npqtr": 27.66,
    "salesqtr": 343.18,
    "flags": [
      "low_roce"
    ],
    "in_working_universe": false
  },
  {
    "rank": 47,
    "symbol": "APARINDS",
    "name": "Apar Inds.",
    "prerank_score": 48.96,
    "qpv": 29.8,
    "qsv": 16.18,
    "roce": 32.7,
    "ret3m": 68.16,
    "cmp": 11714.0,
    "pe": 47.45,
    "mcap": 47052.77,
    "divyld": 0.44,
    "npqtr": 208.93,
    "salesqtr": 5479.73,
    "flags": [],
    "in_working_universe": false
  },
  {
    "rank": 48,
    "symbol": "SHILCTECH",
    "name": "Shilchar Tech.",
    "prerank_score": 48.29,
    "qpv": 21.77,
    "qsv": 10.75,
    "roce": 71.3,
    "ret3m": 66.42,
    "cmp": 4966.8,
    "pe": 30.71,
    "mcap": 5684.57,
    "divyld": 0.25,
    "npqtr": 42.34,
    "salesqtr": 170.26,
    "flags": [],
    "in_working_universe": false
  },
  {
    "rank": 49,
    "symbol": "SKIPPER",
    "name": "Skipper",
    "prerank_score": 48.18,
    "qpv": 39.71,
    "qsv": 20.73,
    "roce": 24.42,
    "ret3m": 36.48,
    "cmp": 465.2,
    "pe": 28.57,
    "mcap": 5250.83,
    "divyld": 0.02,
    "npqtr": 50.17,
    "salesqtr": 1370.59,
    "flags": [],
    "in_working_universe": false
  },
  {
    "rank": 50,
    "symbol": "KIRLOSENG",
    "name": "Kirloskar Oil",
    "prerank_score": 48.14,
    "qpv": 79.61,
    "qsv": 28.82,
    "roce": 13.68,
    "ret3m": 50.8,
    "cmp": 1663.3,
    "pe": 44.43,
    "mcap": 24150.36,
    "divyld": 0.39,
    "npqtr": 109.13,
    "salesqtr": 1872.6,
    "flags": [
      "low_roce"
    ],
    "in_working_universe": false
  },
  {
    "rank": 51,
    "symbol": "TECHNOE",
    "name": "Techno Elec.Engg",
    "prerank_score": 47.24,
    "qpv": 24.23,
    "qsv": 37.12,
    "roce": 16.54,
    "ret3m": 37.85,
    "cmp": 1251.3,
    "pe": 31.0,
    "mcap": 14534.74,
    "divyld": 0.72,
    "npqtr": 119.25,
    "salesqtr": 872.2,
    "flags": [],
    "in_working_universe": false
  },
  {
    "rank": 52,
    "symbol": "ZENTEC",
    "name": "Zen Technologies",
    "prerank_score": 46.84,
    "qpv": 37.89,
    "qsv": 16.83,
    "roce": 37.22,
    "ret3m": 32.93,
    "cmp": 1742.7,
    "pe": 60.06,
    "mcap": 15754.55,
    "divyld": 0.11,
    "npqtr": 55.71,
    "salesqtr": 177.82,
    "flags": [],
    "in_working_universe": false
  },
  {
    "rank": 53,
    "symbol": "MANINDS",
    "name": "Man Industries",
    "prerank_score": 46.01,
    "qpv": 61.31,
    "qsv": 13.45,
    "roce": 15.98,
    "ret3m": 64.3,
    "cmp": 531.75,
    "pe": 21.22,
    "mcap": 3985.29,
    "divyld": 0.0,
    "npqtr": 55.04,
    "salesqtr": 830.38,
    "flags": [],
    "in_working_universe": false
  },
  {
    "rank": 54,
    "symbol": "GOKULAGRO",
    "name": "Gokul Agro",
    "prerank_score": 45.9,
    "qpv": 7.17,
    "qsv": 26.58,
    "roce": 34.2,
    "ret3m": 35.92,
    "cmp": 210.28,
    "pe": 20.73,
    "mcap": 6202.07,
    "divyld": 0.0,
    "npqtr": 77.7,
    "salesqtr": 6314.25,
    "flags": [],
    "in_working_universe": false
  },
  {
    "rank": 55,
    "symbol": "DEEPINDS",
    "name": "Deep Industries",
    "prerank_score": 45.08,
    "qpv": 56.07,
    "qsv": 43.06,
    "roce": 12.06,
    "ret3m": 34.0,
    "cmp": 474.15,
    "pe": 13.07,
    "mcap": 3028.84,
    "divyld": 0.64,
    "npqtr": 71.35,
    "salesqtr": 221.5,
    "flags": [
      "low_roce"
    ],
    "in_working_universe": false
  },
  {
    "rank": 56,
    "symbol": "AEROFLEX",
    "name": "Aeroflex",
    "prerank_score": 44.49,
    "qpv": 8.42,
    "qsv": 21.13,
    "roce": 22.34,
    "ret3m": 78.67,
    "cmp": 289.11,
    "pe": 77.86,
    "mcap": 3824.42,
    "divyld": 0.1,
    "npqtr": 16.49,
    "salesqtr": 120.89,
    "flags": [],
    "in_working_universe": false
  },
  {
    "rank": 57,
    "symbol": "GOLDIAM",
    "name": "Goldiam Intl.",
    "prerank_score": 44.27,
    "qpv": 37.52,
    "qsv": 14.33,
    "roce": 24.59,
    "ret3m": 40.68,
    "cmp": 411.5,
    "pe": 29.72,
    "mcap": 4652.28,
    "divyld": 0.73,
    "npqtr": 68.39,
    "salesqtr": 319.71,
    "flags": [],
    "in_working_universe": false
  },
  {
    "rank": 58,
    "symbol": "AARTIIND",
    "name": "Aarti Industries",
    "prerank_score": 44.02,
    "qpv": 221.74,
    "qsv": 25.77,
    "roce": 6.32,
    "ret3m": 32.71,
    "cmp": 451.2,
    "pe": 44.08,
    "mcap": 16352.92,
    "divyld": 0.22,
    "npqtr": 133.0,
    "salesqtr": 2318.0,
    "flags": [
      "low_roce"
    ],
    "in_working_universe": false
  },
  {
    "rank": 59,
    "symbol": "SONACOMS",
    "name": "Sona BLW Precis.",
    "prerank_score": 43.78,
    "qpv": 16.27,
    "qsv": 38.24,
    "roce": 17.82,
    "ret3m": 30.79,
    "cmp": 581.3,
    "pe": 55.5,
    "mcap": 36204.47,
    "divyld": 0.55,
    "npqtr": 150.16,
    "salesqtr": 1199.76,
    "flags": [],
    "in_working_universe": false
  },
  {
    "rank": 60,
    "symbol": "KSHINTL",
    "name": "KSH Internationa",
    "prerank_score": 42.76,
    "qpv": -4.62,
    "qsv": 58.52,
    "roce": 21.45,
    "ret3m": 72.18,
    "cmp": 601.85,
    "pe": 61.15,
    "mcap": 4084.77,
    "divyld": 0.0,
    "npqtr": 23.33,
    "salesqtr": 817.77,
    "flags": [
      "neg_qpv"
    ],
    "in_working_universe": false
  },
  {
    "rank": 61,
    "symbol": "FINCABLES",
    "name": "Finolex Cables",
    "prerank_score": 42.49,
    "qpv": 11.4,
    "qsv": 35.23,
    "roce": 17.67,
    "ret3m": 33.65,
    "cmp": 953.5,
    "pe": 21.45,
    "mcap": 14605.91,
    "divyld": 0.84,
    "npqtr": 164.03,
    "salesqtr": 1598.62,
    "flags": [],
    "in_working_universe": false
  },
  {
    "rank": 62,
    "symbol": "INGERRAND",
    "name": "Ingersoll-Rand",
    "prerank_score": 42.16,
    "qpv": 15.75,
    "qsv": 19.39,
    "roce": 60.02,
    "ret3m": 30.47,
    "cmp": 4076.3,
    "pe": 46.42,
    "mcap": 12854.12,
    "divyld": 1.96,
    "npqtr": 71.89,
    "salesqtr": 455.48,
    "flags": [],
    "in_working_universe": false
  },
  {
    "rank": 63,
    "symbol": "ROLEXRINGS",
    "name": "Rolex Rings",
    "prerank_score": 42.13,
    "qpv": 57.61,
    "qsv": 5.76,
    "roce": 22.81,
    "ret3m": 35.81,
    "cmp": 161.76,
    "pe": 22.29,
    "mcap": 4407.79,
    "divyld": 0.0,
    "npqtr": 47.75,
    "salesqtr": 274.84,
    "flags": [],
    "in_working_universe": false
  },
  {
    "rank": 64,
    "symbol": "ROSSELLIND",
    "name": "Rossell Techsys",
    "prerank_score": 41.72,
    "qpv": 18.27,
    "qsv": 71.55,
    "roce": 8.18,
    "ret3m": 46.02,
    "cmp": 939.0,
    "pe": 160.66,
    "mcap": 3529.67,
    "divyld": 0.02,
    "npqtr": 5.41,
    "salesqtr": 129.93,
    "flags": [
      "low_roce"
    ],
    "in_working_universe": false
  },
  {
    "rank": 65,
    "symbol": "SHILPAMED",
    "name": "Shilpa Medicare",
    "prerank_score": 41.36,
    "qpv": 69.92,
    "qsv": 28.32,
    "roce": 7.82,
    "ret3m": 48.91,
    "cmp": 405.25,
    "pe": 44.86,
    "mcap": 7936.57,
    "divyld": 0.12,
    "npqtr": 44.58,
    "salesqtr": 409.73,
    "flags": [
      "low_roce"
    ],
    "in_working_universe": false
  },
  {
    "rank": 66,
    "symbol": "MAHLOG",
    "name": "Mahindra Logis.",
    "prerank_score": 41.1,
    "qpv": 146.23,
    "qsv": 19.06,
    "roce": 5.64,
    "ret3m": 50.46,
    "cmp": 425.95,
    "pe": null,
    "mcap": null,
    "divyld": 0.59,
    "npqtr": 6.01,
    "salesqtr": 1898.03,
    "flags": [
      "low_roce"
    ],
    "in_working_universe": false
  },
  {
    "rank": 67,
    "symbol": "IMFA",
    "name": "Indian Metals",
    "prerank_score": 40.65,
    "qpv": 40.69,
    "qsv": 9.27,
    "roce": 21.29,
    "ret3m": 37.18,
    "cmp": 1499.2,
    "pe": 21.97,
    "mcap": 8093.29,
    "divyld": 1.33,
    "npqtr": 131.46,
    "salesqtr": 702.83,
    "flags": [],
    "in_working_universe": false
  },
  {
    "rank": 68,
    "symbol": "WABAG",
    "name": "Va Tech Wabag",
    "prerank_score": 40.48,
    "qpv": 35.67,
    "qsv": 18.53,
    "roce": 19.7,
    "ret3m": 35.33,
    "cmp": 1487.1,
    "pe": 26.81,
    "mcap": 9258.25,
    "divyld": 0.27,
    "npqtr": 91.3,
    "salesqtr": 961.3,
    "flags": [],
    "in_working_universe": false
  },
  {
    "rank": 69,
    "symbol": "KSB",
    "name": "KSB",
    "prerank_score": 40.46,
    "qpv": 33.43,
    "qsv": 7.93,
    "roce": 24.52,
    "ret3m": 44.63,
    "cmp": 990.05,
    "pe": 59.75,
    "mcap": 17259.75,
    "divyld": 0.44,
    "npqtr": 81.0,
    "salesqtr": 784.0,
    "flags": [],
    "in_working_universe": false
  },
  {
    "rank": 70,
    "symbol": "AMBER",
    "name": "Amber Enterp.",
    "prerank_score": 39.88,
    "qpv": 26.43,
    "qsv": 37.94,
    "roce": 14.49,
    "ret3m": 35.87,
    "cmp": 7858.5,
    "pe": 119.14,
    "mcap": 27692.15,
    "divyld": 0.0,
    "npqtr": -9.34,
    "salesqtr": 2942.82,
    "flags": [
      "low_roce"
    ],
    "in_working_universe": false
  },
  {
    "rank": 71,
    "symbol": "STLTECH",
    "name": "Sterlite Tech.",
    "prerank_score": 39.57,
    "qpv": 53.33,
    "qsv": 25.95,
    "roce": 2.86,
    "ret3m": 200.72,
    "cmp": 278.47,
    "pe": null,
    "mcap": null,
    "divyld": 0.0,
    "npqtr": -17.0,
    "salesqtr": 1257.0,
    "flags": [
      "low_roce"
    ],
    "in_working_universe": false
  },
  {
    "rank": 72,
    "symbol": "SHRIPISTON",
    "name": "Shriram Pistons",
    "prerank_score": 39.5,
    "qpv": 17.91,
    "qsv": 20.67,
    "roce": 25.7,
    "ret3m": 30.49,
    "cmp": 3586.8,
    "pe": 28.15,
    "mcap": 15801.31,
    "divyld": 0.28,
    "npqtr": 125.7,
    "salesqtr": 1023.2,
    "flags": [],
    "in_working_universe": false
  },
  {
    "rank": 73,
    "symbol": "GESHIP",
    "name": "GE Shipping Co",
    "prerank_score": 38.89,
    "qpv": 142.21,
    "qsv": 17.59,
    "roce": 13.86,
    "ret3m": 31.99,
    "cmp": 1445.6,
    "pe": 9.13,
    "mcap": 20650.75,
    "divyld": 2.05,
    "npqtr": 812.52,
    "salesqtr": 1454.44,
    "flags": [
      "low_roce"
    ],
    "in_working_universe": false
  },
  {
    "rank": 74,
    "symbol": "PARKHOSPS",
    "name": "Park Medi World",
    "prerank_score": 38.47,
    "qpv": 11.38,
    "qsv": 17.76,
    "roce": 20.36,
    "ret3m": 49.51,
    "cmp": 224.31,
    "pe": 45.75,
    "mcap": 9686.02,
    "divyld": 0.0,
    "npqtr": 52.85,
    "salesqtr": 409.97,
    "flags": [],
    "in_working_universe": false
  },
  {
    "rank": 75,
    "symbol": "ISGEC",
    "name": "ISGEC Heavy",
    "prerank_score": 38.35,
    "qpv": 102.88,
    "qsv": 16.26,
    "roce": 14.83,
    "ret3m": 40.42,
    "cmp": 1047.0,
    "pe": 23.37,
    "mcap": 7652.84,
    "divyld": 0.48,
    "npqtr": 84.44,
    "salesqtr": 1738.56,
    "flags": [
      "low_roce"
    ],
    "in_working_universe": false
  },
  {
    "rank": 76,
    "symbol": "AZAD",
    "name": "Azad Engineering",
    "prerank_score": 37.29,
    "qpv": 40.14,
    "qsv": 31.38,
    "roce": 12.23,
    "ret3m": 32.64,
    "cmp": 1862.6,
    "pe": 97.86,
    "mcap": 12042.35,
    "divyld": 0.0,
    "npqtr": 34.04,
    "salesqtr": 155.8,
    "flags": [
      "low_roce"
    ],
    "in_working_universe": false
  },
  {
    "rank": 77,
    "symbol": "SANSERA",
    "name": "Sansera Enginee.",
    "prerank_score": 37.07,
    "qpv": 44.51,
    "qsv": 24.71,
    "roce": 13.38,
    "ret3m": 38.15,
    "cmp": 2374.6,
    "pe": 54.03,
    "mcap": 14787.4,
    "divyld": 0.14,
    "npqtr": 69.42,
    "salesqtr": 907.67,
    "flags": [
      "low_roce"
    ],
    "in_working_universe": false
  },
  {
    "rank": 78,
    "symbol": "SIGMAADV",
    "name": "Sigma Advanced",
    "prerank_score": 36.75,
    "qpv": 3.15,
    "qsv": 667.25,
    "roce": 8.74,
    "ret3m": 30.48,
    "cmp": 216.19,
    "pe": 26.63,
    "mcap": 3814.76,
    "divyld": 0.0,
    "npqtr": -1.03,
    "salesqtr": 145.7,
    "flags": [
      "low_roce"
    ],
    "in_working_universe": false
  },
  {
    "rank": 79,
    "symbol": "ABSLAMC",
    "name": "Aditya AMC",
    "prerank_score": 36.61,
    "qpv": 21.01,
    "qsv": 7.41,
    "roce": 35.51,
    "ret3m": 32.73,
    "cmp": 1037.85,
    "pe": 29.44,
    "mcap": 29975.16,
    "divyld": 2.31,
    "npqtr": 269.52,
    "salesqtr": 478.08,
    "flags": [],
    "in_working_universe": false
  },
  {
    "rank": 80,
    "symbol": "THERMAX",
    "name": "Thermax",
    "prerank_score": 35.98,
    "qpv": 40.63,
    "qsv": 4.19,
    "roce": 16.22,
    "ret3m": 40.82,
    "cmp": 4125.1,
    "pe": 76.76,
    "mcap": 49187.24,
    "divyld": 0.34,
    "npqtr": 205.01,
    "salesqtr": 2634.68,
    "flags": [],
    "in_working_universe": false
  },
  {
    "rank": 81,
    "symbol": "AVANTIFEED",
    "name": "Avanti Feeds",
    "prerank_score": 35.82,
    "qpv": 10.4,
    "qsv": 1.31,
    "roce": 23.99,
    "ret3m": 95.94,
    "cmp": 1463.0,
    "pe": 31.6,
    "mcap": 19989.91,
    "divyld": 0.62,
    "npqtr": 163.47,
    "salesqtr": 1383.52,
    "flags": [],
    "in_working_universe": false
  },
  {
    "rank": 82,
    "symbol": "BHARATFORG",
    "name": "Bharat Forge",
    "prerank_score": 35.64,
    "qpv": 40.77,
    "qsv": 24.96,
    "roce": 12.18,
    "ret3m": 37.38,
    "cmp": 1895.8,
    "pe": 77.67,
    "mcap": 90694.36,
    "divyld": 0.45,
    "npqtr": 272.8,
    "salesqtr": 4342.93,
    "flags": [
      "low_roce"
    ],
    "in_working_universe": false
  },
  {
    "rank": 83,
    "symbol": "BHEL",
    "name": "B H E L",
    "prerank_score": 35.01,
    "qpv": 189.83,
    "qsv": 16.44,
    "roce": 4.87,
    "ret3m": 31.81,
    "cmp": 332.61,
    "pe": 142.25,
    "mcap": 115827.58,
    "divyld": 0.15,
    "npqtr": 390.4,
    "salesqtr": 8473.1,
    "flags": [
      "low_roce"
    ],
    "in_working_universe": false
  },
  {
    "rank": 84,
    "symbol": "AEQUS",
    "name": "Aequs",
    "prerank_score": 34.99,
    "qpv": 17.87,
    "qsv": 50.77,
    "roce": 1.11,
    "ret3m": 40.58,
    "cmp": 190.36,
    "pe": null,
    "mcap": 12720.38,
    "divyld": 0.0,
    "npqtr": -42.68,
    "salesqtr": 326.17,
    "flags": [
      "low_roce"
    ],
    "in_working_universe": false
  },
  {
    "rank": 85,
    "symbol": "ATHERENRGY",
    "name": "Ather Energy",
    "prerank_score": 34.4,
    "qpv": 59.76,
    "qsv": 50.2,
    "roce": -65.71,
    "ret3m": 46.12,
    "cmp": 896.1,
    "pe": null,
    "mcap": 34295.19,
    "divyld": 0.0,
    "npqtr": -84.6,
    "salesqtr": 953.6,
    "flags": [
      "roce_zero",
      "low_roce",
      "neg_roce"
    ],
    "in_working_universe": false
  },
  {
    "rank": 86,
    "symbol": "SMSPHARMA",
    "name": "SMS Pharma.",
    "prerank_score": 31.38,
    "qpv": 35.93,
    "qsv": 21.4,
    "roce": 12.19,
    "ret3m": 36.74,
    "cmp": 408.1,
    "pe": 43.87,
    "mcap": 3830.2,
    "divyld": 0.1,
    "npqtr": 23.34,
    "salesqtr": 210.45,
    "flags": [
      "low_roce"
    ],
    "in_working_universe": false
  },
  {
    "rank": 87,
    "symbol": "DHENU",
    "name": "Dhenu Buildcon",
    "prerank_score": 30.65,
    "qpv": 4150.0,
    "qsv": -0.08,
    "roce": null,
    "ret3m": 39.89,
    "cmp": 9.75,
    "pe": null,
    "mcap": 4382.92,
    "divyld": 0.0,
    "npqtr": 0.81,
    "salesqtr": 0.84,
    "flags": [
      "roce_zero",
      "neg_qsv"
    ],
    "in_working_universe": false
  },
  {
    "rank": 88,
    "symbol": "IBULHSGFIN",
    "name": "Indiabulls",
    "prerank_score": 29.58,
    "qpv": 2250.95,
    "qsv": -8.9,
    "roce": null,
    "ret3m": 45.46,
    "cmp": 17.47,
    "pe": 141.57,
    "mcap": 4063.09,
    "divyld": 0.0,
    "npqtr": 78.37,
    "salesqtr": 96.96,
    "flags": [
      "roce_zero",
      "neg_qsv"
    ],
    "in_working_universe": false
  },
  {
    "rank": 89,
    "symbol": "HFCL",
    "name": "HFCL",
    "prerank_score": 28.66,
    "qpv": 32.55,
    "qsv": 19.65,
    "roce": 7.55,
    "ret3m": 57.76,
    "cmp": 97.84,
    "pe": 288.92,
    "mcap": 14969.0,
    "divyld": 0.1,
    "npqtr": 102.37,
    "salesqtr": 1210.79,
    "flags": [
      "low_roce"
    ],
    "in_working_universe": false
  },
  {
    "rank": 90,
    "symbol": "WELCORP",
    "name": "Welspun Corp",
    "prerank_score": 25.87,
    "qpv": -32.91,
    "qsv": 25.43,
    "roce": 21.24,
    "ret3m": 46.68,
    "cmp": 1100.6,
    "pe": 18.69,
    "mcap": 29005.86,
    "divyld": 0.45,
    "npqtr": 456.36,
    "salesqtr": 4532.48,
    "flags": [
      "neg_qpv"
    ],
    "in_working_universe": false
  },
  {
    "rank": 91,
    "symbol": "TRUALT",
    "name": "TruAlt Bioenergy",
    "prerank_score": 24.98,
    "qpv": -7.79,
    "qsv": 71.82,
    "roce": 14.18,
    "ret3m": 35.53,
    "cmp": 457.0,
    "pe": 26.51,
    "mcap": 3918.04,
    "divyld": 0.0,
    "npqtr": 69.19,
    "salesqtr": 713.24,
    "flags": [
      "neg_qpv",
      "low_roce"
    ],
    "in_working_universe": false
  },
  {
    "rank": 92,
    "symbol": "STEELCAST",
    "name": "Steelcast",
    "prerank_score": 22.27,
    "qpv": 7.18,
    "qsv": -4.33,
    "roce": 32.94,
    "ret3m": 62.75,
    "cmp": 296.79,
    "pe": 33.32,
    "mcap": 3013.82,
    "divyld": 0.49,
    "npqtr": 20.59,
    "salesqtr": 97.4,
    "flags": [
      "neg_qsv"
    ],
    "in_working_universe": false
  },
  {
    "rank": 93,
    "symbol": "PAISALO",
    "name": "Paisalo Digital",
    "prerank_score": 21.29,
    "qpv": 7.06,
    "qsv": 17.82,
    "roce": 13.13,
    "ret3m": 38.7,
    "cmp": 44.51,
    "pe": 19.18,
    "mcap": 4052.01,
    "divyld": 0.22,
    "npqtr": 66.26,
    "salesqtr": 240.05,
    "flags": [
      "low_roce"
    ],
    "in_working_universe": false
  },
  {
    "rank": 94,
    "symbol": "AGIIL",
    "name": "AGI Infra",
    "prerank_score": 20.6,
    "qpv": 36.92,
    "qsv": -4.28,
    "roce": 22.03,
    "ret3m": 33.36,
    "cmp": 365.95,
    "pe": 54.58,
    "mcap": 4579.82,
    "divyld": 0.03,
    "npqtr": 26.11,
    "salesqtr": 87.5,
    "flags": [
      "neg_qsv"
    ],
    "in_working_universe": false
  },
  {
    "rank": 95,
    "symbol": "BELRISE",
    "name": "Belrise Industri",
    "prerank_score": 20.25,
    "qpv": 25.79,
    "qsv": 8.02,
    "roce": 14.3,
    "ret3m": 32.51,
    "cmp": 219.05,
    "pe": 40.47,
    "mcap": 19473.53,
    "divyld": 0.25,
    "npqtr": 121.97,
    "salesqtr": 2340.52,
    "flags": [
      "low_roce"
    ],
    "in_working_universe": false
  },
  {
    "rank": 96,
    "symbol": "ABB",
    "name": "A B B",
    "prerank_score": 20.18,
    "qpv": -18.35,
    "qsv": 5.71,
    "roce": 29.93,
    "ret3m": 54.12,
    "cmp": 7255.0,
    "pe": 92.11,
    "mcap": 153788.94,
    "divyld": 0.54,
    "npqtr": 432.85,
    "salesqtr": 3557.01,
    "flags": [
      "neg_qpv"
    ],
    "in_working_universe": false
  },
  {
    "rank": 97,
    "symbol": "ACMESOLAR",
    "name": "ACME Solar Hold.",
    "prerank_score": 18.19,
    "qpv": -3.66,
    "qsv": 42.34,
    "roce": 8.42,
    "ret3m": 45.09,
    "cmp": 296.25,
    "pe": 35.79,
    "mcap": 17957.92,
    "divyld": 0.07,
    "npqtr": 113.7,
    "salesqtr": 496.79,
    "flags": [
      "neg_qpv",
      "low_roce"
    ],
    "in_working_universe": false
  },
  {
    "rank": 98,
    "symbol": "PITTIENG",
    "name": "Pitti Engg.",
    "prerank_score": 13.71,
    "qpv": -1.88,
    "qsv": 15.05,
    "roce": 17.05,
    "ret3m": 34.56,
    "cmp": 921.8,
    "pe": 27.27,
    "mcap": 3472.91,
    "divyld": 0.16,
    "npqtr": 28.22,
    "salesqtr": 477.42,
    "flags": [
      "neg_qpv"
    ],
    "in_working_universe": false
  },
  {
    "rank": 99,
    "symbol": "JAYNECOIND",
    "name": "Jayaswal Neco",
    "prerank_score": 12.48,
    "qpv": 6.08,
    "qsv": 4.25,
    "roce": 12.59,
    "ret3m": 35.72,
    "cmp": 98.95,
    "pe": 25.17,
    "mcap": 9599.98,
    "divyld": 0.0,
    "npqtr": 74.09,
    "salesqtr": 1727.23,
    "flags": [
      "low_roce"
    ],
    "in_working_universe": false
  },
  {
    "rank": 100,
    "symbol": "NAVA",
    "name": "Nava",
    "prerank_score": 12.45,
    "qpv": -11.98,
    "qsv": 17.64,
    "roce": 17.17,
    "ret3m": 30.16,
    "cmp": 692.0,
    "pe": 21.87,
    "mcap": 19569.75,
    "divyld": 1.16,
    "npqtr": 325.71,
    "salesqtr": 991.12,
    "flags": [
      "neg_qpv"
    ],
    "in_working_universe": false
  },
  {
    "rank": 101,
    "symbol": "LUXIND",
    "name": "Lux Industries",
    "prerank_score": 11.49,
    "qpv": -46.66,
    "qsv": 21.59,
    "roce": 12.54,
    "ret3m": 66.07,
    "cmp": 1462.55,
    "pe": 38.96,
    "mcap": 4416.06,
    "divyld": 0.14,
    "npqtr": 13.32,
    "salesqtr": 672.53,
    "flags": [
      "neg_qpv",
      "low_roce"
    ],
    "in_working_universe": false
  },
  {
    "rank": 102,
    "symbol": "PFC",
    "name": "Power Fin.Corpn.",
    "prerank_score": 11.06,
    "qpv": 8.14,
    "qsv": 8.57,
    "roce": 9.73,
    "ret3m": 31.72,
    "cmp": 471.1,
    "pe": 6.16,
    "mcap": 155467.79,
    "divyld": 3.35,
    "npqtr": 8211.9,
    "salesqtr": 29094.81,
    "flags": [
      "low_roce"
    ],
    "in_working_universe": false
  },
  {
    "rank": 103,
    "symbol": "SGMART",
    "name": "SG Mart",
    "prerank_score": 10.75,
    "qpv": -61.7,
    "qsv": 23.21,
    "roce": 11.33,
    "ret3m": 71.79,
    "cmp": 548.6,
    "pe": 67.24,
    "mcap": 6907.18,
    "divyld": 0.0,
    "npqtr": 10.74,
    "salesqtr": 1644.43,
    "flags": [
      "neg_qpv",
      "low_roce"
    ],
    "in_working_universe": false
  },
  {
    "rank": 104,
    "symbol": "E2E",
    "name": "E2E Networks",
    "prerank_score": 7.7,
    "qpv": -52.68,
    "qsv": 185.66,
    "roce": -0.51,
    "ret3m": 37.79,
    "cmp": 2844.4,
    "pe": null,
    "mcap": 5847.08,
    "divyld": 0.0,
    "npqtr": 6.44,
    "salesqtr": 95.64,
    "flags": [
      "roce_zero",
      "neg_qpv",
      "low_roce",
      "neg_roce"
    ],
    "in_working_universe": false
  },
  {
    "rank": 105,
    "symbol": "SUVENLIFE",
    "name": "Suven Life Scie.",
    "prerank_score": 6.93,
    "qpv": -160.53,
    "qsv": 74.53,
    "roce": -86.96,
    "ret3m": 55.86,
    "cmp": 210.5,
    "pe": null,
    "mcap": 5534.99,
    "divyld": 0.0,
    "npqtr": -101.92,
    "salesqtr": 2.81,
    "flags": [
      "roce_zero",
      "neg_qpv",
      "low_roce",
      "neg_roce"
    ],
    "in_working_universe": false
  },
  {
    "rank": 106,
    "symbol": "ADANIENSOL",
    "name": "Adani Energy Sol",
    "prerank_score": 3.91,
    "qpv": -1.69,
    "qsv": 15.43,
    "roce": 10.23,
    "ret3m": 40.7,
    "cmp": 1265.3,
    "pe": 67.57,
    "mcap": 151757.3,
    "divyld": 0.0,
    "npqtr": 574.06,
    "salesqtr": 6729.65,
    "flags": [
      "neg_qpv",
      "low_roce"
    ],
    "in_working_universe": false
  },
  {
    "rank": 107,
    "symbol": "GARFIBRES",
    "name": "Garware Hi Tech",
    "prerank_score": 0.25,
    "qpv": -8.29,
    "qsv": -1.64,
    "roce": 20.57,
    "ret3m": 45.21,
    "cmp": 3927.2,
    "pe": 29.7,
    "mcap": 9142.21,
    "divyld": 0.31,
    "npqtr": 55.77,
    "salesqtr": 458.74,
    "flags": [
      "neg_qpv",
      "neg_qsv"
    ],
    "in_working_universe": false
  },
  {
    "rank": 108,
    "symbol": "GALLANTT",
    "name": "Gallantt Ispat L",
    "prerank_score": 0.09,
    "qpv": -11.67,
    "qsv": -4.0,
    "roce": 19.2,
    "ret3m": 58.58,
    "cmp": 862.45,
    "pe": 43.44,
    "mcap": 20827.25,
    "divyld": 0.14,
    "npqtr": 100.41,
    "salesqtr": 1073.58,
    "flags": [
      "neg_qpv",
      "neg_qsv"
    ],
    "in_working_universe": false
  },
  {
    "rank": 109,
    "symbol": "DALMIASUG",
    "name": "Dalmia Bharat",
    "prerank_score": 0.04,
    "qpv": 17.64,
    "qsv": -16.7,
    "roce": 9.48,
    "ret3m": 44.81,
    "cmp": 382.95,
    "pe": 9.11,
    "mcap": 3084.17,
    "divyld": 1.57,
    "npqtr": 69.77,
    "salesqtr": 697.75,
    "flags": [
      "neg_qsv",
      "low_roce"
    ],
    "in_working_universe": false
  },
  {
    "rank": 110,
    "symbol": "ADANIPOWER",
    "name": "Adani Power",
    "prerank_score": -0.22,
    "qpv": -18.89,
    "qsv": -8.92,
    "roce": 22.54,
    "ret3m": 47.48,
    "cmp": 202.98,
    "pe": 34.18,
    "mcap": 391499.21,
    "divyld": 0.0,
    "npqtr": 2488.09,
    "salesqtr": 12451.44,
    "flags": [
      "neg_qpv",
      "neg_qsv"
    ],
    "in_working_universe": false
  },
  {
    "rank": 111,
    "symbol": "RPSGVENT",
    "name": "RPSG Ventures",
    "prerank_score": -0.7,
    "qpv": -203.72,
    "qsv": 15.57,
    "roce": 11.33,
    "ret3m": 41.54,
    "cmp": 937.6,
    "pe": null,
    "mcap": 3102.34,
    "divyld": 0.0,
    "npqtr": -136.3,
    "salesqtr": 2756.4,
    "flags": [
      "neg_qpv",
      "low_roce"
    ],
    "in_working_universe": false
  },
  {
    "rank": 112,
    "symbol": "SUPPETRO",
    "name": "Supreme Petroch.",
    "prerank_score": -1.71,
    "qpv": -50.25,
    "qsv": -10.01,
    "roce": 22.76,
    "ret3m": 46.39,
    "cmp": 773.4,
    "pe": 53.69,
    "mcap": 14578.14,
    "divyld": 1.29,
    "npqtr": 30.15,
    "salesqtr": 1264.69,
    "flags": [
      "neg_qpv",
      "neg_qsv"
    ],
    "in_working_universe": false
  },
  {
    "rank": 113,
    "symbol": "VTL",
    "name": "Vardhman Textile",
    "prerank_score": -4.09,
    "qpv": -21.02,
    "qsv": 1.62,
    "roce": 10.83,
    "ret3m": 39.06,
    "cmp": 560.35,
    "pe": 20.33,
    "mcap": 16221.71,
    "divyld": 0.89,
    "npqtr": 168.5,
    "salesqtr": 2505.31,
    "flags": [
      "neg_qpv",
      "low_roce"
    ],
    "in_working_universe": false
  },
  {
    "rank": 114,
    "symbol": "KTKBANK",
    "name": "Karnataka Bank",
    "prerank_score": -5.53,
    "qpv": 2.54,
    "qsv": -1.02,
    "roce": 6.33,
    "ret3m": 38.45,
    "cmp": 250.32,
    "pe": 8.2,
    "mcap": 9469.34,
    "divyld": 2.0,
    "npqtr": 290.79,
    "salesqtr": 2220.05,
    "flags": [
      "neg_qsv",
      "low_roce"
    ],
    "in_working_universe": false
  },
  {
    "rank": 115,
    "symbol": "ADANIGREEN",
    "name": "Adani Green",
    "prerank_score": -8.59,
    "qpv": -106.78,
    "qsv": 11.88,
    "roce": 8.7,
    "ret3m": 30.88,
    "cmp": 1150.0,
    "pe": 114.7,
    "mcap": 189113.55,
    "divyld": 0.0,
    "npqtr": 5.0,
    "salesqtr": 2618.0,
    "flags": [
      "neg_qpv",
      "low_roce"
    ],
    "in_working_universe": false
  },
  {
    "rank": 116,
    "symbol": "GUJALKALI",
    "name": "Gujarat Alkalies",
    "prerank_score": -19.31,
    "qpv": -77.65,
    "qsv": 1.46,
    "roce": -0.34,
    "ret3m": 57.04,
    "cmp": 719.7,
    "pe": null,
    "mcap": 5271.49,
    "divyld": 2.2,
    "npqtr": -19.95,
    "salesqtr": 1044.46,
    "flags": [
      "roce_zero",
      "neg_qpv",
      "low_roce",
      "neg_roce"
    ],
    "in_working_universe": false
  },
  {
    "rank": 117,
    "symbol": "GOKEX",
    "name": "Gokaldas Exports",
    "prerank_score": -20.38,
    "qpv": -70.98,
    "qsv": -0.92,
    "roce": 10.62,
    "ret3m": 36.27,
    "cmp": 768.5,
    "pe": 48.11,
    "mcap": 5630.22,
    "divyld": 0.0,
    "npqtr": 14.61,
    "salesqtr": 978.65,
    "flags": [
      "neg_qpv",
      "neg_qsv",
      "low_roce"
    ],
    "in_working_universe": false
  },
  {
    "rank": 118,
    "symbol": "JINDALPOLY",
    "name": "Jindal Poly Film",
    "prerank_score": -21.63,
    "qpv": -453.42,
    "qsv": -68.66,
    "roce": 5.36,
    "ret3m": 98.28,
    "cmp": 728.1,
    "pe": null,
    "mcap": null,
    "divyld": 0.81,
    "npqtr": -96.92,
    "salesqtr": 371.66,
    "flags": [
      "neg_qpv",
      "neg_qsv",
      "low_roce"
    ],
    "in_working_universe": false
  }
]